imr/farms/__init__.py
imr/farms/wfs.py
imr_farms-1.0.0.dist-info/LICENSE
imr_farms-1.0.0.dist-info/METADATA
imr_farms-1.0.0.dist-info/WHEEL
imr_farms-1.0.0.dist-info/top_level.txt
imr_farms-1.0.0.dist-info/RECORD
